{
  "status": "completed",
  "run_name": "rastrigin_d2_beta3_ula_seed2_mlp256x3_eps_seed2",
  "sample_run_name": "rastrigin_d2_beta3_ula_seed2",
  "snapshot": -1,
  "n_training_samples": 8192,
  "dim": 2,
  "n_params": 149250,
  "wall_clock_seconds": 52.78,
  "device": "cuda",
  "gpu_name": "NVIDIA RTX A6000",
  "peak_gpu_memory_mb": 26.3,
  "final_loss": 0.558056,
  "loss_history": [
    0.760549,
    0.607791,
    0.583968,
    0.565483,
    0.563871,
    0.567011,
    0.562375,
    0.565981,
    0.566106,
    0.559912,
    0.560422,
    0.569234,
    0.564207,
    0.564717,
    0.560918,
    0.566703,
    0.56412,
    0.560726,
    0.564743,
    0.563407,
    0.561539,
    0.562702,
    0.558321,
    0.566171,
    0.561762,
    0.562465,
    0.563975,
    0.565176,
    0.561623,
    0.565917,
    0.565626,
    0.561919,
    0.562292,
    0.561519,
    0.56643,
    0.560983,
    0.561803,
    0.564318,
    0.55809,
    0.558056
  ]
}