{
  "status": "completed",
  "run_name": "many_well_d10_beta1_ula_seed0_mlp256x3_eps_seed0",
  "sample_run_name": "many_well_d10_beta1_ula_seed0",
  "snapshot": -1,
  "n_training_samples": 8192,
  "dim": 10,
  "n_params": 153354,
  "wall_clock_seconds": 52.32,
  "device": "cuda",
  "gpu_name": "NVIDIA RTX A6000",
  "peak_gpu_memory_mb": 25.6,
  "final_loss": 2.506355,
  "loss_history": [
    4.099235,
    2.993688,
    2.866749,
    2.794947,
    2.773215,
    2.744289,
    2.768763,
    2.754814,
    2.756622,
    2.74813,
    2.756382,
    2.74454,
    2.743848,
    2.736856,
    2.728213,
    2.728689,
    2.723737,
    2.696959,
    2.683531,
    2.67524,
    2.648967,
    2.630365,
    2.618606,
    2.597621,
    2.577205,
    2.563821,
    2.562048,
    2.549219,
    2.549697,
    2.531907,
    2.53708,
    2.522412,
    2.521892,
    2.514167,
    2.503803,
    2.513313,
    2.507221,
    2.519136,
    2.49957,
    2.506355
  ]
}