{
  "status": "completed",
  "run_name": "many_well_d20_beta4_ula_seed2_mlp256x3_eps_seed2",
  "sample_run_name": "many_well_d20_beta4_ula_seed2",
  "snapshot": -1,
  "n_training_samples": 8192,
  "dim": 20,
  "n_params": 158484,
  "wall_clock_seconds": 42.46,
  "device": "cuda",
  "gpu_name": "NVIDIA RTX A6000",
  "peak_gpu_memory_mb": 28.6,
  "final_loss": 4.619054,
  "loss_history": [
    8.330973,
    5.972648,
    5.490716,
    5.098715,
    4.913533,
    4.810139,
    4.784729,
    4.743723,
    4.751472,
    4.728566,
    4.715287,
    4.732162,
    4.717225,
    4.714579,
    4.716813,
    4.728066,
    4.706401,
    4.686846,
    4.71471,
    4.691382,
    4.684067,
    4.685867,
    4.680016,
    4.686673,
    4.661981,
    4.658221,
    4.672431,
    4.682495,
    4.657257,
    4.676256,
    4.644168,
    4.635406,
    4.635835,
    4.635637,
    4.654002,
    4.6273,
    4.624967,
    4.614609,
    4.599216,
    4.619054
  ]
}