{
  "status": "completed",
  "run_name": "rastrigin_d2_beta0p1_ula_seed0_mlp256x3_eps_seed0",
  "sample_run_name": "rastrigin_d2_beta0p1_ula_seed0",
  "snapshot": -1,
  "n_training_samples": 8192,
  "dim": 2,
  "n_params": 149250,
  "wall_clock_seconds": 52.27,
  "device": "cuda",
  "gpu_name": "NVIDIA L4",
  "peak_gpu_memory_mb": 22.4,
  "final_loss": 0.826349,
  "loss_history": [
    1.141059,
    0.838812,
    0.834074,
    0.833224,
    0.825424,
    0.832359,
    0.828027,
    0.827206,
    0.830138,
    0.826159,
    0.827841,
    0.826509,
    0.828628,
    0.827774,
    0.828266,
    0.82719,
    0.829167,
    0.828165,
    0.829118,
    0.826521,
    0.827623,
    0.825562,
    0.823757,
    0.823114,
    0.825945,
    0.826393,
    0.827766,
    0.826827,
    0.826451,
    0.82845,
    0.827792,
    0.820595,
    0.822647,
    0.825545,
    0.828012,
    0.822782,
    0.82428,
    0.825794,
    0.823506,
    0.826349
  ]
}