{
  "status": "completed",
  "run_name": "double_well_d5_beta7_ula_seed0_mlp256x3_eps_seed0",
  "sample_run_name": "double_well_d5_beta7_ula_seed0",
  "snapshot": -1,
  "n_training_samples": 8192,
  "dim": 5,
  "n_params": 150789,
  "wall_clock_seconds": 47.84,
  "device": "cuda",
  "gpu_name": "NVIDIA RTX A6000",
  "peak_gpu_memory_mb": 25.9,
  "final_loss": 0.606846,
  "loss_history": [
    1.380139,
    0.867612,
    0.770145,
    0.704825,
    0.674105,
    0.652388,
    0.64982,
    0.635622,
    0.633506,
    0.625614,
    0.620679,
    0.621679,
    0.616552,
    0.615986,
    0.613873,
    0.619919,
    0.619365,
    0.616185,
    0.62,
    0.61649,
    0.614465,
    0.60923,
    0.613625,
    0.612279,
    0.604209,
    0.606565,
    0.611781,
    0.607599,
    0.608203,
    0.612693,
    0.610529,
    0.609084,
    0.609865,
    0.609308,
    0.606702,
    0.606764,
    0.605042,
    0.610349,
    0.60537,
    0.606846
  ]
}