{
  "status": "completed",
  "run_name": "rastrigin_d20_beta4_ula_seed2_mlp256x3_eps_seed2",
  "sample_run_name": "rastrigin_d20_beta4_ula_seed2",
  "snapshot": -1,
  "n_training_samples": 8192,
  "dim": 20,
  "n_params": 158484,
  "wall_clock_seconds": 54.22,
  "device": "cuda",
  "gpu_name": "NVIDIA RTX A6000",
  "peak_gpu_memory_mb": 28.6,
  "final_loss": 5.613446,
  "loss_history": [
    8.876343,
    6.161005,
    5.862359,
    5.733582,
    5.700728,
    5.663487,
    5.674216,
    5.643581,
    5.660897,
    5.645092,
    5.635055,
    5.66285,
    5.646404,
    5.645284,
    5.653375,
    5.677125,
    5.642272,
    5.618905,
    5.651362,
    5.631905,
    5.628244,
    5.623673,
    5.626096,
    5.644078,
    5.60806,
    5.611706,
    5.630931,
    5.645321,
    5.624734,
    5.642725,
    5.623923,
    5.610225,
    5.620305,
    5.624232,
    5.656022,
    5.616334,
    5.627771,
    5.611683,
    5.601379,
    5.613446
  ]
}