{
  "status": "completed",
  "run_name": "rastrigin_d20_beta2_ula_seed1_mlp256x3_eps_seed1",
  "sample_run_name": "rastrigin_d20_beta2_ula_seed1",
  "snapshot": -1,
  "n_training_samples": 8192,
  "dim": 20,
  "n_params": 158484,
  "wall_clock_seconds": 54.84,
  "device": "cuda",
  "gpu_name": "NVIDIA RTX A6000",
  "peak_gpu_memory_mb": 27.4,
  "final_loss": 5.63006,
  "loss_history": [
    8.784768,
    6.093562,
    5.842957,
    5.757462,
    5.681425,
    5.694221,
    5.681304,
    5.684087,
    5.665698,
    5.657198,
    5.690444,
    5.658337,
    5.622017,
    5.669227,
    5.631393,
    5.655444,
    5.631383,
    5.650946,
    5.66512,
    5.653268,
    5.628706,
    5.642772,
    5.66069,
    5.626629,
    5.636315,
    5.663639,
    5.645754,
    5.654727,
    5.634513,
    5.653961,
    5.627021,
    5.627463,
    5.642039,
    5.628381,
    5.60743,
    5.627779,
    5.633163,
    5.657024,
    5.639256,
    5.63006
  ]
}