{
  "status": "completed",
  "run_name": "rastrigin_d2_beta8_ula_seed2_mlp256x3_eps_seed2",
  "sample_run_name": "rastrigin_d2_beta8_ula_seed2",
  "snapshot": -1,
  "n_training_samples": 8192,
  "dim": 2,
  "n_params": 149250,
  "wall_clock_seconds": 77.79,
  "device": "cuda",
  "gpu_name": "NVIDIA RTX A6000",
  "peak_gpu_memory_mb": 25.7,
  "final_loss": 0.551062,
  "loss_history": [
    0.75146,
    0.601297,
    0.578478,
    0.559928,
    0.557882,
    0.56027,
    0.555833,
    0.559199,
    0.559501,
    0.553104,
    0.553545,
    0.562814,
    0.557844,
    0.558235,
    0.554474,
    0.560306,
    0.557672,
    0.554719,
    0.558362,
    0.557631,
    0.555093,
    0.556796,
    0.551318,
    0.55986,
    0.555444,
    0.55562,
    0.557862,
    0.5584,
    0.555235,
    0.558977,
    0.558849,
    0.555893,
    0.55504,
    0.554659,
    0.560159,
    0.554824,
    0.555714,
    0.558084,
    0.551463,
    0.551062
  ]
}