{
  "status": "completed",
  "seed": 1,
  "energy": "ackley",
  "dim": 10,
  "beta_m": 50.0,
  "sampler": "ULA",
  "n_particles": 8192,
  "n_steps": 10000,
  "burn_in": 2000,
  "trace_every": 100,
  "step_size": 0.001,
  "wall_clock_seconds": 5.63,
  "mean_energy": 3.3819,
  "median_energy": 3.428,
  "min_energy": 0.0741,
  "std_energy": 0.9017,
  "energy_quantiles": {
    "q01": 0.2637,
    "q05": 2.1289,
    "q25": 2.7631,
    "q75": 3.9797,
    "q95": 4.7617
  },
  "acceptance_rate": {
    "mean": 1.0
  },
  "traces": {
    "steps": [
      100,
      200,
      300,
      400,
      500,
      600,
      700,
      800,
      900,
      1000,
      1100,
      1200,
      1300,
      1400,
      1500,
      1600,
      1700,
      1800,
      1900,
      2000,
      2100,
      2200,
      2300,
      2400,
      2500,
      2600,
      2700,
      2800,
      2900,
      3000,
      3100,
      3200,
      3300,
      3400,
      3500,
      3600,
      3700,
      3800,
      3900,
      4000,
      4100,
      4200,
      4300,
      4400,
      4500,
      4600,
      4700,
      4800,
      4900,
      5000,
      5100,
      5200,
      5300,
      5400,
      5500,
      5600,
      5700,
      5800,
      5900,
      6000,
      6100,
      6200,
      6300,
      6400,
      6500,
      6600,
      6700,
      6800,
      6900,
      7000,
      7100,
      7200,
      7300,
      7400,
      7500,
      7600,
      7700,
      7800,
      7900,
      8000,
      8100,
      8200,
      8300,
      8400,
      8500,
      8600,
      8700,
      8800,
      8900,
      9000,
      9100,
      9200,
      9300,
      9400,
      9500,
      9600,
      9700,
      9800,
      9900,
      10000
    ],
    "mean_energy": [
      3.4498,
      3.4486,
      3.4472,
      3.4471,
      3.446,
      3.4444,
      3.4434,
      3.443,
      3.4448,
      3.4437,
      3.4421,
      3.4398,
      3.4395,
      3.4388,
      3.4365,
      3.4359,
      3.4355,
      3.4344,
      3.4332,
      3.4337,
      3.4332,
      3.431,
      3.4312,
      3.4299,
      3.4299,
      3.4283,
      3.4282,
      3.4275,
      3.4251,
      3.4255,
      3.4241,
      3.424,
      3.4228,
      3.4216,
      3.4211,
      3.4214,
      3.4203,
      3.4187,
      3.4176,
      3.4174,
      3.4175,
      3.4155,
      3.415,
      3.4154,
      3.413,
      3.4141,
      3.4138,
      3.4114,
      3.4092,
      3.4102,
      3.4075,
      3.4082,
      3.4078,
      3.407,
      3.4056,
      3.4056,
      3.4038,
      3.4035,
      3.4024,
      3.4019,
      3.4018,
      3.4016,
      3.4012,
      3.4015,
      3.3993,
      3.3988,
      3.3978,
      3.3981,
      3.3972,
      3.3966,
      3.3976,
      3.3953,
      3.3955,
      3.395,
      3.3931,
      3.3931,
      3.3916,
      3.3913,
      3.3908,
      3.3914,
      3.3908,
      3.3906,
      3.3898,
      3.3903,
      3.3885,
      3.3882,
      3.3887,
      3.3868,
      3.3862,
      3.3872,
      3.3863,
      3.3857,
      3.3864,
      3.3847,
      3.3844,
      3.383,
      3.3838,
      3.3838,
      3.383,
      3.3819
    ],
    "median_energy": [
      3.4762,
      3.4791,
      3.4773,
      3.4732,
      3.4778,
      3.4762,
      3.4711,
      3.4744,
      3.4799,
      3.4784,
      3.4785,
      3.4698,
      3.4724,
      3.4743,
      3.4704,
      3.4704,
      3.4773,
      3.4729,
      3.469,
      3.4722,
      3.4715,
      3.465,
      3.471,
      3.4674,
      3.4669,
      3.4692,
      3.4661,
      3.4644,
      3.4653,
      3.4658,
      3.4654,
      3.4612,
      3.4616,
      3.4594,
      3.46,
      3.4584,
      3.4571,
      3.4602,
      3.4572,
      3.4593,
      3.4588,
      3.4559,
      3.4604,
      3.4624,
      3.4586,
      3.4545,
      3.4572,
      3.4565,
      3.4546,
      3.4547,
      3.4522,
      3.4576,
      3.4542,
      3.456,
      3.446,
      3.4549,
      3.4445,
      3.4496,
      3.4478,
      3.4476,
      3.4488,
      3.4411,
      3.4477,
      3.444,
      3.4472,
      3.4444,
      3.4436,
      3.4463,
      3.4402,
      3.4454,
      3.4478,
      3.4367,
      3.4441,
      3.4393,
      3.4361,
      3.4376,
      3.4382,
      3.4327,
      3.4368,
      3.4354,
      3.4333,
      3.4322,
      3.4368,
      3.4355,
      3.43,
      3.4321,
      3.4359,
      3.4352,
      3.4333,
      3.4327,
      3.4368,
      3.4322,
      3.4318,
      3.4324,
      3.4232,
      3.4266,
      3.4261,
      3.4261,
      3.4219,
      3.428
    ],
    "min_energy": [
      0.097,
      0.1219,
      0.1071,
      0.1235,
      0.1533,
      0.1132,
      0.1035,
      0.1167,
      0.129,
      0.0612,
      0.1273,
      0.0994,
      0.1462,
      0.1373,
      0.0861,
      0.1083,
      0.1223,
      0.101,
      0.1072,
      0.1583,
      0.107,
      0.0837,
      0.0993,
      0.0912,
      0.1206,
      0.1099,
      0.1152,
      0.1181,
      0.1405,
      0.1001,
      0.1067,
      0.1201,
      0.088,
      0.1412,
      0.1047,
      0.1079,
      0.082,
      0.0958,
      0.0897,
      0.1224,
      0.1172,
      0.0637,
      0.1168,
      0.1217,
      0.1216,
      0.0979,
      0.1129,
      0.0707,
      0.1269,
      0.0883,
      0.1391,
      0.0426,
      0.0959,
      0.0939,
      0.0834,
      0.0942,
      0.1288,
      0.0767,
      0.107,
      0.0972,
      0.1174,
      0.086,
      0.1231,
      0.0793,
      0.101,
      0.1208,
      0.1111,
      0.1026,
      0.1068,
      0.1169,
      0.1092,
      0.1262,
      0.1195,
      0.0848,
      0.0983,
      0.1144,
      0.1092,
      0.1113,
      0.1259,
      0.1235,
      0.1134,
      0.114,
      0.0729,
      0.118,
      0.1007,
      0.1049,
      0.1125,
      0.1037,
      0.1057,
      0.1192,
      0.0781,
      0.1,
      0.1263,
      0.0999,
      0.1032,
      0.103,
      0.1018,
      0.0911,
      0.1164,
      0.0741
    ],
    "q05_energy": [
      2.1576,
      2.1573,
      2.1539,
      2.152,
      2.1541,
      2.1506,
      2.1629,
      2.1537,
      2.1533,
      2.1523,
      2.1516,
      2.148,
      2.1502,
      2.1496,
      2.1423,
      2.1478,
      2.1461,
      2.1403,
      2.1432,
      2.138,
      2.1531,
      2.1507,
      2.1377,
      2.1471,
      2.1446,
      2.1463,
      2.1396,
      2.1388,
      2.1374,
      2.1374,
      2.1404,
      2.1426,
      2.1397,
      2.1332,
      2.1471,
      2.1433,
      2.1456,
      2.1371,
      2.1421,
      2.1402,
      2.1379,
      2.1323,
      2.1359,
      2.1409,
      2.1346,
      2.1427,
      2.1386,
      2.1321,
      2.1342,
      2.1444,
      2.1338,
      2.1322,
      2.1319,
      2.1334,
      2.1379,
      2.1371,
      2.1318,
      2.1293,
      2.1358,
      2.1336,
      2.1446,
      2.1322,
      2.1317,
      2.1336,
      2.129,
      2.1318,
      2.1364,
      2.1308,
      2.1354,
      2.1296,
      2.1365,
      2.1309,
      2.1371,
      2.1352,
      2.1332,
      2.1392,
      2.1261,
      2.1383,
      2.135,
      2.1397,
      2.1358,
      2.1359,
      2.1324,
      2.1326,
      2.1331,
      2.1314,
      2.1287,
      2.1336,
      2.1293,
      2.1302,
      2.1381,
      2.1343,
      2.1348,
      2.1358,
      2.1367,
      2.1304,
      2.1264,
      2.1295,
      2.1273,
      2.1289
    ],
    "q95_energy": [
      4.7911,
      4.7787,
      4.7772,
      4.7807,
      4.7735,
      4.7747,
      4.7769,
      4.7739,
      4.7823,
      4.7746,
      4.7697,
      4.7828,
      4.7793,
      4.7903,
      4.7748,
      4.7762,
      4.7772,
      4.7854,
      4.7701,
      4.7771,
      4.7762,
      4.7715,
      4.7655,
      4.7752,
      4.7678,
      4.7654,
      4.7606,
      4.7802,
      4.7701,
      4.7811,
      4.7683,
      4.7801,
      4.7697,
      4.7675,
      4.7721,
      4.7691,
      4.7635,
      4.7695,
      4.7594,
      4.7719,
      4.7843,
      4.7756,
      4.7711,
      4.7734,
      4.7779,
      4.7678,
      4.7712,
      4.7821,
      4.7648,
      4.7631,
      4.7691,
      4.7632,
      4.7805,
      4.7711,
      4.7728,
      4.7728,
      4.7754,
      4.7653,
      4.777,
      4.7741,
      4.7695,
      4.7764,
      4.7764,
      4.7746,
      4.7737,
      4.7726,
      4.7555,
      4.7706,
      4.7655,
      4.7723,
      4.7724,
      4.769,
      4.7708,
      4.7727,
      4.766,
      4.7683,
      4.7608,
      4.7703,
      4.7562,
      4.7698,
      4.776,
      4.7586,
      4.7629,
      4.7721,
      4.7644,
      4.7683,
      4.7668,
      4.7562,
      4.7742,
      4.7649,
      4.7664,
      4.7655,
      4.7699,
      4.7646,
      4.7584,
      4.7635,
      4.7686,
      4.7658,
      4.7672,
      4.7617
    ],
    "mean_x_norm": [
      2.8207,
      2.8187,
      2.818,
      2.818,
      2.8169,
      2.8154,
      2.8141,
      2.8138,
      2.8118,
      2.8125,
      2.8121,
      2.8104,
      2.811,
      2.8086,
      2.8069,
      2.8076,
      2.8069,
      2.807,
      2.8061,
      2.804,
      2.8045,
      2.8022,
      2.8027,
      2.8016,
      2.8002,
      2.8016,
      2.7998,
      2.7992,
      2.7983,
      2.7976,
      2.7955,
      2.7965,
      2.7943,
      2.7947,
      2.7925,
      2.7921,
      2.7917,
      2.7923,
      2.7909,
      2.7915,
      2.7895,
      2.7901,
      2.7886,
      2.7882,
      2.788,
      2.7866,
      2.7859,
      2.7855,
      2.7849,
      2.7832,
      2.7831,
      2.7826,
      2.7814,
      2.7812,
      2.781,
      2.7797,
      2.7799,
      2.777,
      2.7771,
      2.7778,
      2.7767,
      2.7763,
      2.7771,
      2.7743,
      2.7742,
      2.774,
      2.7733,
      2.7741,
      2.773,
      2.7716,
      2.7713,
      2.7711,
      2.7704,
      2.7708,
      2.7696,
      2.77,
      2.7688,
      2.767,
      2.7678,
      2.767,
      2.7667,
      2.767,
      2.766,
      2.7646,
      2.7643,
      2.7638,
      2.7639,
      2.7637,
      2.7635,
      2.7635,
      2.7631,
      2.7623,
      2.762,
      2.7622,
      2.7603,
      2.7601,
      2.7591,
      2.7609,
      2.7598,
      2.7579
    ],
    "mean_displacement": [
      0.2327,
      0.2325,
      0.2313,
      0.2321,
      0.2323,
      0.2311,
      0.2307,
      0.2318,
      0.2318,
      0.2334,
      0.2325,
      0.2323,
      0.2323,
      0.2327,
      0.2328,
      0.2306,
      0.2317,
      0.2316,
      0.2314,
      0.2321,
      0.2316,
      0.232,
      0.2314,
      0.2309,
      0.2328,
      0.2323,
      0.2319,
      0.2323,
      0.2315,
      0.231,
      0.2326,
      0.2306,
      0.2319,
      0.2315,
      0.2318,
      0.2322,
      0.2317,
      0.2322,
      0.2311,
      0.2306,
      0.232,
      0.2316,
      0.2315,
      0.2318,
      0.2318,
      0.2305,
      0.2321,
      0.2328,
      0.2315,
      0.2312,
      0.2308,
      0.2312,
      0.232,
      0.2314,
      0.232,
      0.2317,
      0.2322,
      0.2321,
      0.23,
      0.2301,
      0.2302,
      0.2315,
      0.231,
      0.2317,
      0.2322,
      0.2309,
      0.2306,
      0.2313,
      0.2312,
      0.23,
      0.2315,
      0.2318,
      0.2306,
      0.2313,
      0.2315,
      0.2304,
      0.2307,
      0.2318,
      0.2313,
      0.231,
      0.2313,
      0.2311,
      0.2328,
      0.2323,
      0.2317,
      0.2304,
      0.2321,
      0.2318,
      0.23,
      0.2303,
      0.2319,
      0.2311,
      0.2319,
      0.2312,
      0.2313,
      0.2307,
      0.231,
      0.232,
      0.2309,
      0.2312
    ]
  }
}