{
  "dim": 10,
  "beta_h": 50.0,
  "n_smc": 32,
  "n_ula": 10,
  "oracle_cost_per_run": 1441792,
  "n_restarts": 69,
  "wall_seconds": 6.44,
  "restarts": [
    {
      "restart_id": 0,
      "best_energy": 0.0648,
      "mean_energy": 0.2805,
      "q01": 0.1235,
      "q05": 0.1562,
      "q10": 0.1779,
      "q50": 0.2729,
      "q90": 0.3919
    },
    {
      "restart_id": 1,
      "best_energy": 0.0716,
      "mean_energy": 0.2802,
      "q01": 0.1159,
      "q05": 0.1553,
      "q10": 0.1789,
      "q50": 0.273,
      "q90": 0.3924
    },
    {
      "restart_id": 2,
      "best_energy": 0.0693,
      "mean_energy": 0.2794,
      "q01": 0.1175,
      "q05": 0.1549,
      "q10": 0.1783,
      "q50": 0.2708,
      "q90": 0.3926
    },
    {
      "restart_id": 3,
      "best_energy": 0.0833,
      "mean_energy": 0.2816,
      "q01": 0.1267,
      "q05": 0.1579,
      "q10": 0.1795,
      "q50": 0.2745,
      "q90": 0.3929
    },
    {
      "restart_id": 4,
      "best_energy": 0.0784,
      "mean_energy": 0.2817,
      "q01": 0.1214,
      "q05": 0.1574,
      "q10": 0.1793,
      "q50": 0.2742,
      "q90": 0.3909
    },
    {
      "restart_id": 5,
      "best_energy": 0.0699,
      "mean_energy": 0.2804,
      "q01": 0.1161,
      "q05": 0.1559,
      "q10": 0.1776,
      "q50": 0.2724,
      "q90": 0.394
    },
    {
      "restart_id": 6,
      "best_energy": 0.0781,
      "mean_energy": 0.28,
      "q01": 0.1166,
      "q05": 0.1535,
      "q10": 0.1779,
      "q50": 0.2704,
      "q90": 0.3945
    },
    {
      "restart_id": 7,
      "best_energy": 0.0589,
      "mean_energy": 0.2811,
      "q01": 0.1155,
      "q05": 0.155,
      "q10": 0.1801,
      "q50": 0.2737,
      "q90": 0.3922
    },
    {
      "restart_id": 8,
      "best_energy": 0.08,
      "mean_energy": 0.2805,
      "q01": 0.1253,
      "q05": 0.1558,
      "q10": 0.1761,
      "q50": 0.2714,
      "q90": 0.3965
    },
    {
      "restart_id": 9,
      "best_energy": 0.0765,
      "mean_energy": 0.2802,
      "q01": 0.1216,
      "q05": 0.1574,
      "q10": 0.1768,
      "q50": 0.273,
      "q90": 0.3929
    },
    {
      "restart_id": 10,
      "best_energy": 0.0716,
      "mean_energy": 0.2805,
      "q01": 0.1197,
      "q05": 0.1593,
      "q10": 0.1792,
      "q50": 0.2732,
      "q90": 0.3871
    },
    {
      "restart_id": 11,
      "best_energy": 0.0609,
      "mean_energy": 0.2806,
      "q01": 0.115,
      "q05": 0.1562,
      "q10": 0.1773,
      "q50": 0.2736,
      "q90": 0.3928
    },
    {
      "restart_id": 12,
      "best_energy": 0.0629,
      "mean_energy": 0.2814,
      "q01": 0.1218,
      "q05": 0.1549,
      "q10": 0.179,
      "q50": 0.2762,
      "q90": 0.3944
    },
    {
      "restart_id": 13,
      "best_energy": 0.0469,
      "mean_energy": 0.2791,
      "q01": 0.1135,
      "q05": 0.1524,
      "q10": 0.1766,
      "q50": 0.2748,
      "q90": 0.3847
    },
    {
      "restart_id": 14,
      "best_energy": 0.0645,
      "mean_energy": 0.2812,
      "q01": 0.116,
      "q05": 0.155,
      "q10": 0.1806,
      "q50": 0.2736,
      "q90": 0.3927
    },
    {
      "restart_id": 15,
      "best_energy": 0.0533,
      "mean_energy": 0.2826,
      "q01": 0.1206,
      "q05": 0.1583,
      "q10": 0.1783,
      "q50": 0.2743,
      "q90": 0.3966
    },
    {
      "restart_id": 16,
      "best_energy": 0.0717,
      "mean_energy": 0.2784,
      "q01": 0.1169,
      "q05": 0.1531,
      "q10": 0.1755,
      "q50": 0.271,
      "q90": 0.3887
    },
    {
      "restart_id": 17,
      "best_energy": 0.0663,
      "mean_energy": 0.2829,
      "q01": 0.1184,
      "q05": 0.1581,
      "q10": 0.1787,
      "q50": 0.2756,
      "q90": 0.397
    },
    {
      "restart_id": 18,
      "best_energy": 0.0734,
      "mean_energy": 0.2805,
      "q01": 0.1217,
      "q05": 0.1587,
      "q10": 0.1799,
      "q50": 0.2713,
      "q90": 0.3973
    },
    {
      "restart_id": 19,
      "best_energy": 0.0716,
      "mean_energy": 0.2806,
      "q01": 0.1231,
      "q05": 0.1569,
      "q10": 0.1799,
      "q50": 0.2707,
      "q90": 0.3965
    },
    {
      "restart_id": 20,
      "best_energy": 0.0621,
      "mean_energy": 0.2803,
      "q01": 0.118,
      "q05": 0.1569,
      "q10": 0.18,
      "q50": 0.2718,
      "q90": 0.3931
    },
    {
      "restart_id": 21,
      "best_energy": 0.0897,
      "mean_energy": 0.2804,
      "q01": 0.1185,
      "q05": 0.1543,
      "q10": 0.1776,
      "q50": 0.2734,
      "q90": 0.3924
    },
    {
      "restart_id": 22,
      "best_energy": 0.0569,
      "mean_energy": 0.2803,
      "q01": 0.1189,
      "q05": 0.1533,
      "q10": 0.1784,
      "q50": 0.2732,
      "q90": 0.39
    },
    {
      "restart_id": 23,
      "best_energy": 0.0718,
      "mean_energy": 0.281,
      "q01": 0.1211,
      "q05": 0.1565,
      "q10": 0.1785,
      "q50": 0.274,
      "q90": 0.3901
    },
    {
      "restart_id": 24,
      "best_energy": 0.0742,
      "mean_energy": 0.2787,
      "q01": 0.1224,
      "q05": 0.1575,
      "q10": 0.1793,
      "q50": 0.2707,
      "q90": 0.3879
    },
    {
      "restart_id": 25,
      "best_energy": 0.0624,
      "mean_energy": 0.2806,
      "q01": 0.1148,
      "q05": 0.1522,
      "q10": 0.176,
      "q50": 0.2722,
      "q90": 0.3938
    },
    {
      "restart_id": 26,
      "best_energy": 0.0715,
      "mean_energy": 0.2821,
      "q01": 0.1221,
      "q05": 0.158,
      "q10": 0.1783,
      "q50": 0.2741,
      "q90": 0.3969
    },
    {
      "restart_id": 27,
      "best_energy": 0.0569,
      "mean_energy": 0.2802,
      "q01": 0.1225,
      "q05": 0.1548,
      "q10": 0.1771,
      "q50": 0.2715,
      "q90": 0.3941
    },
    {
      "restart_id": 28,
      "best_energy": 0.0824,
      "mean_energy": 0.2794,
      "q01": 0.1218,
      "q05": 0.1536,
      "q10": 0.1752,
      "q50": 0.2722,
      "q90": 0.3909
    },
    {
      "restart_id": 29,
      "best_energy": 0.0745,
      "mean_energy": 0.2827,
      "q01": 0.1136,
      "q05": 0.1552,
      "q10": 0.1775,
      "q50": 0.2756,
      "q90": 0.3949
    },
    {
      "restart_id": 30,
      "best_energy": 0.0842,
      "mean_energy": 0.2806,
      "q01": 0.1248,
      "q05": 0.1584,
      "q10": 0.1776,
      "q50": 0.2721,
      "q90": 0.3932
    },
    {
      "restart_id": 31,
      "best_energy": 0.0533,
      "mean_energy": 0.2787,
      "q01": 0.1184,
      "q05": 0.157,
      "q10": 0.1786,
      "q50": 0.2706,
      "q90": 0.391
    },
    {
      "restart_id": 32,
      "best_energy": 0.0669,
      "mean_energy": 0.2806,
      "q01": 0.1201,
      "q05": 0.1539,
      "q10": 0.1761,
      "q50": 0.2725,
      "q90": 0.3939
    },
    {
      "restart_id": 33,
      "best_energy": 0.0682,
      "mean_energy": 0.2792,
      "q01": 0.117,
      "q05": 0.1524,
      "q10": 0.1757,
      "q50": 0.2702,
      "q90": 0.3969
    },
    {
      "restart_id": 34,
      "best_energy": 0.0702,
      "mean_energy": 0.281,
      "q01": 0.1186,
      "q05": 0.156,
      "q10": 0.1783,
      "q50": 0.2739,
      "q90": 0.3941
    },
    {
      "restart_id": 35,
      "best_energy": 0.0725,
      "mean_energy": 0.2813,
      "q01": 0.1206,
      "q05": 0.1571,
      "q10": 0.1804,
      "q50": 0.2755,
      "q90": 0.3914
    },
    {
      "restart_id": 36,
      "best_energy": 0.0532,
      "mean_energy": 0.2802,
      "q01": 0.1224,
      "q05": 0.1577,
      "q10": 0.1777,
      "q50": 0.2707,
      "q90": 0.3931
    },
    {
      "restart_id": 37,
      "best_energy": 0.0558,
      "mean_energy": 0.2802,
      "q01": 0.1173,
      "q05": 0.1534,
      "q10": 0.1759,
      "q50": 0.2737,
      "q90": 0.3915
    },
    {
      "restart_id": 38,
      "best_energy": 0.0743,
      "mean_energy": 0.2815,
      "q01": 0.1173,
      "q05": 0.1551,
      "q10": 0.1784,
      "q50": 0.2739,
      "q90": 0.3952
    },
    {
      "restart_id": 39,
      "best_energy": 0.055,
      "mean_energy": 0.2808,
      "q01": 0.1183,
      "q05": 0.1559,
      "q10": 0.1791,
      "q50": 0.2724,
      "q90": 0.3947
    },
    {
      "restart_id": 40,
      "best_energy": 0.0744,
      "mean_energy": 0.2804,
      "q01": 0.1201,
      "q05": 0.1558,
      "q10": 0.1752,
      "q50": 0.2719,
      "q90": 0.3939
    },
    {
      "restart_id": 41,
      "best_energy": 0.0602,
      "mean_energy": 0.2792,
      "q01": 0.1162,
      "q05": 0.157,
      "q10": 0.1782,
      "q50": 0.2707,
      "q90": 0.3894
    },
    {
      "restart_id": 42,
      "best_energy": 0.0712,
      "mean_energy": 0.2813,
      "q01": 0.1207,
      "q05": 0.1553,
      "q10": 0.1786,
      "q50": 0.2755,
      "q90": 0.3914
    },
    {
      "restart_id": 43,
      "best_energy": 0.064,
      "mean_energy": 0.2789,
      "q01": 0.1195,
      "q05": 0.1545,
      "q10": 0.1765,
      "q50": 0.2721,
      "q90": 0.3877
    },
    {
      "restart_id": 44,
      "best_energy": 0.0725,
      "mean_energy": 0.2796,
      "q01": 0.1218,
      "q05": 0.1592,
      "q10": 0.1807,
      "q50": 0.271,
      "q90": 0.389
    },
    {
      "restart_id": 45,
      "best_energy": 0.037,
      "mean_energy": 0.2791,
      "q01": 0.1206,
      "q05": 0.1573,
      "q10": 0.1783,
      "q50": 0.27,
      "q90": 0.3874
    },
    {
      "restart_id": 46,
      "best_energy": 0.0634,
      "mean_energy": 0.2795,
      "q01": 0.1198,
      "q05": 0.156,
      "q10": 0.1746,
      "q50": 0.2728,
      "q90": 0.3895
    },
    {
      "restart_id": 47,
      "best_energy": 0.0683,
      "mean_energy": 0.2795,
      "q01": 0.1176,
      "q05": 0.1562,
      "q10": 0.1795,
      "q50": 0.2728,
      "q90": 0.3907
    },
    {
      "restart_id": 48,
      "best_energy": 0.0603,
      "mean_energy": 0.2791,
      "q01": 0.1203,
      "q05": 0.1534,
      "q10": 0.1752,
      "q50": 0.2711,
      "q90": 0.3931
    },
    {
      "restart_id": 49,
      "best_energy": 0.054,
      "mean_energy": 0.2783,
      "q01": 0.115,
      "q05": 0.152,
      "q10": 0.1741,
      "q50": 0.2722,
      "q90": 0.3886
    },
    {
      "restart_id": 50,
      "best_energy": 0.0562,
      "mean_energy": 0.2807,
      "q01": 0.123,
      "q05": 0.1577,
      "q10": 0.1793,
      "q50": 0.2717,
      "q90": 0.3969
    },
    {
      "restart_id": 51,
      "best_energy": 0.0752,
      "mean_energy": 0.2811,
      "q01": 0.1245,
      "q05": 0.1575,
      "q10": 0.1789,
      "q50": 0.2722,
      "q90": 0.3929
    },
    {
      "restart_id": 52,
      "best_energy": 0.0689,
      "mean_energy": 0.2794,
      "q01": 0.1193,
      "q05": 0.1555,
      "q10": 0.1774,
      "q50": 0.2728,
      "q90": 0.3906
    },
    {
      "restart_id": 53,
      "best_energy": 0.0405,
      "mean_energy": 0.2798,
      "q01": 0.1208,
      "q05": 0.1568,
      "q10": 0.1775,
      "q50": 0.2724,
      "q90": 0.3909
    },
    {
      "restart_id": 54,
      "best_energy": 0.0805,
      "mean_energy": 0.2818,
      "q01": 0.119,
      "q05": 0.1558,
      "q10": 0.1797,
      "q50": 0.2726,
      "q90": 0.3966
    },
    {
      "restart_id": 55,
      "best_energy": 0.0523,
      "mean_energy": 0.2789,
      "q01": 0.1145,
      "q05": 0.1517,
      "q10": 0.1748,
      "q50": 0.2711,
      "q90": 0.3932
    },
    {
      "restart_id": 56,
      "best_energy": 0.0432,
      "mean_energy": 0.2813,
      "q01": 0.1204,
      "q05": 0.1574,
      "q10": 0.1787,
      "q50": 0.2736,
      "q90": 0.3968
    },
    {
      "restart_id": 57,
      "best_energy": 0.0714,
      "mean_energy": 0.2796,
      "q01": 0.1186,
      "q05": 0.1556,
      "q10": 0.1804,
      "q50": 0.271,
      "q90": 0.3927
    },
    {
      "restart_id": 58,
      "best_energy": 0.0322,
      "mean_energy": 0.2789,
      "q01": 0.1143,
      "q05": 0.1552,
      "q10": 0.1764,
      "q50": 0.2715,
      "q90": 0.3934
    },
    {
      "restart_id": 59,
      "best_energy": 0.0722,
      "mean_energy": 0.2787,
      "q01": 0.122,
      "q05": 0.1543,
      "q10": 0.1765,
      "q50": 0.2709,
      "q90": 0.3886
    },
    {
      "restart_id": 60,
      "best_energy": 0.0755,
      "mean_energy": 0.2799,
      "q01": 0.1259,
      "q05": 0.1577,
      "q10": 0.1769,
      "q50": 0.2725,
      "q90": 0.3893
    },
    {
      "restart_id": 61,
      "best_energy": 0.0691,
      "mean_energy": 0.2812,
      "q01": 0.1233,
      "q05": 0.156,
      "q10": 0.1816,
      "q50": 0.2738,
      "q90": 0.3921
    },
    {
      "restart_id": 62,
      "best_energy": 0.0604,
      "mean_energy": 0.2793,
      "q01": 0.1132,
      "q05": 0.153,
      "q10": 0.1752,
      "q50": 0.2721,
      "q90": 0.3929
    },
    {
      "restart_id": 63,
      "best_energy": 0.0648,
      "mean_energy": 0.2822,
      "q01": 0.1146,
      "q05": 0.1601,
      "q10": 0.1815,
      "q50": 0.2747,
      "q90": 0.395
    },
    {
      "restart_id": 64,
      "best_energy": 0.0718,
      "mean_energy": 0.2806,
      "q01": 0.1148,
      "q05": 0.1516,
      "q10": 0.1751,
      "q50": 0.2715,
      "q90": 0.3992
    },
    {
      "restart_id": 65,
      "best_energy": 0.0637,
      "mean_energy": 0.2811,
      "q01": 0.1191,
      "q05": 0.1574,
      "q10": 0.1783,
      "q50": 0.2707,
      "q90": 0.3982
    },
    {
      "restart_id": 66,
      "best_energy": 0.0704,
      "mean_energy": 0.2803,
      "q01": 0.1189,
      "q05": 0.1575,
      "q10": 0.1791,
      "q50": 0.2715,
      "q90": 0.3943
    },
    {
      "restart_id": 67,
      "best_energy": 0.0739,
      "mean_energy": 0.2808,
      "q01": 0.1205,
      "q05": 0.1567,
      "q10": 0.1777,
      "q50": 0.2739,
      "q90": 0.3924
    },
    {
      "restart_id": 68,
      "best_energy": 0.0769,
      "mean_energy": 0.2789,
      "q01": 0.1248,
      "q05": 0.1571,
      "q10": 0.1779,
      "q50": 0.2726,
      "q90": 0.3876
    }
  ]
}