{
  "status": "completed",
  "seed": 1,
  "energy": "many_well",
  "dim": 10,
  "beta_m": 0.5,
  "sampler": "ULA",
  "n_particles": 8192,
  "n_steps": 10000,
  "burn_in": 2000,
  "save_every": 100,
  "step_size": 0.001,
  "wall_clock_seconds": 32.66,
  "device": "cuda",
  "gpu_name": "NVIDIA RTX A6000",
  "peak_gpu_memory_mb": 79.8,
  "n_energy_evals": 98304000,
  "n_grad_evals": 98304000,
  "mean_energy": -9.5142,
  "median_energy": -10.0627,
  "min_energy": -19.1588,
  "std_energy": 4.231,
  "energy_quantiles": {
    "q01": -16.9766,
    "q05": -15.4878,
    "q25": -12.591,
    "q75": -6.9892,
    "q95": -1.7225
  },
  "nan_count": 0,
  "diverged_count": 0,
  "acceptance_rate": {
    "mean": 1.0,
    "min": 1.0,
    "max": 1.0
  }
}